pylogformatter/__init__.py
pylogformatter/celery.py
pylogformatter/generic.py
pylogformatter/json.py
pylogformatter/replace_celery_logger.py
pylogformatter-0.0.1.dist-info/LICENSE
pylogformatter-0.0.1.dist-info/WHEEL
pylogformatter-0.0.1.dist-info/METADATA
pylogformatter-0.0.1.dist-info/RECORD
