Metadata-Version: 2.1
Name: pylogformatter
Version: 0.0.1
Summary: python logging formatter. JSONFormatter、GenericFormatter、CeleryTaskFormatter
Author: Bin Wen
Author-email: caowb@pillar-biosciences.com
Classifier: License :: OSI Approved :: MIT License
Classifier: Operating System :: OS Independent
Classifier: Programming Language :: Python :: 3
Classifier: Programming Language :: Python :: 3.7
Classifier: Programming Language :: Python :: 3.8
Classifier: Programming Language :: Python :: 3.9
